[{"ID":1,"NOME":"Natal ALL Net","DESCRICAO":"Oi Livre pra falar com qualquer operadora.\nCom R$ 10,00:\n500 MB de Internet 4G .\n150 minutos para fixo e celular de qualquer operadora de todo Brasil.\nR$ 0,30/min para qualquer operadora quando acabar a franquia.\n300 SMS pra qualquer operadora.\nOi WiFi\nApp Oi Toca Aí","SCRIPT":"Oi (nome do cliente), você já conhece o novo Oi Livre? Agora na nova oferta, o que você não usar no período de validade da oferta acumula e você tem ainda mais internet e minutos pra falar com qualquer operadora. Por isso você não precisa mais ter um monte de chips. \nFunciona assim: os benefícios da oferta são concedidos de acordo com o valor dos seus créditos. Por exemplo: com R$10 de créditos no momento da adesão, você terá 150 minutos pra falar com qualquer operadora do Brasil, usando o 14/31, 500MB de internet, 300 SMS's para enviar para qualquer operadora e acesso ao Aplicativo Oi Toca Aí. Tudo isso válido por 10 dias. Assim, a  sua recarga só será debitada novamente ao término da oferta, renovando seus benefícios. E tem mais: o que você não usar no período de validade, acumula por mais tempo, basta fazer uma recarga ou ter créditos no seu Oi ao término da oferta. \nAgora se você tiver R$20 de créditos, você leva 300 minutos, 1 Giga de internet e 600 SMS válidos por 20 dias. A oferta é renovada desde que haja saldo de créditos a partir de R$1 no seu Oi e os novos benefícios e validade dependerão do valor dos seus créditos.Você pode converter até R$30 de créditos em benefícios. Se quiser ler o regulamento da oferta, acesse oi.com.br/oilivre","PRECO":null,"EXIBIR":null,"ID_PROGRAMA":"78","ID_BENEFICIO":"42"}]
